loone/__init__.py
loone/data/__init__.py
loone/data/data.py
loone/data/model_variables.py
loone/data/tp_variables_regions.py
loone/loone_nut/LOONE_NUT.py
loone/loone_nut/__init__.py
loone/loone_nut/all_stations_bc_quantiles.py
loone/loone_nut/forecast_bias_corrections.py
loone/loone_q/LOONE_Q.py
loone/loone_q/__init__.py
loone/loone_wq/LOONE_WQ.py
loone/loone_wq/__init__.py
loone/utils/__init__.py
loone/utils/ap_functions.py
loone/utils/dec_tree_functions.py
loone/utils/df_wsms.py
loone/utils/lo_functions.py
loone/utils/lonino_functions.py
loone/utils/loone_nchla_fns.py
loone/utils/stg_sto_ar.py
loone/utils/thc_class.py
loone/utils/tp_mass_balance_functions_regions.py
loone/utils/trib_hc.py
loone/utils/wca_stages_class.py
loone-1.3.0.dist-info/licenses/LICENSE
loone-1.3.0.dist-info/METADATA
loone-1.3.0.dist-info/WHEEL
loone-1.3.0.dist-info/top_level.txt
loone-1.3.0.dist-info/RECORD
