Metadata-Version: 2.4
Name: loone
Version: 1.3.0
Summary: LOONE: A comprehensive water balance-nutrient-optimization model
Author-email: Osama Tarabih <osamatarabih@usf.edu>
Maintainer-email: Michael Souffront <msouffront@aquaveo.com>, James Dolinar <jdolinar@aquaveo.com>
License: BSD-3-Clause License
License-File: LICENSE
Requires-Dist: matplotlib
Requires-Dist: numpy
Requires-Dist: pandas
Requires-Dist: platypus-opt==1.0.4
Requires-Dist: scipy
Requires-Dist: pyyaml
Dynamic: license-file
